attrdictionary/__init__.py
attrdictionary/default.py
attrdictionary/dictionary.py
attrdictionary/mapping.py
attrdictionary/merge.py
attrdictionary/mixins.py
attrdictionary-1.0.0.dist-info/LICENSE.txt
attrdictionary-1.0.0.dist-info/METADATA
attrdictionary-1.0.0.dist-info/WHEEL
attrdictionary-1.0.0.dist-info/top_level.txt
attrdictionary-1.0.0.dist-info/zip-safe
attrdictionary-1.0.0.dist-info/RECORD
